GeeksforgeeksDatabaseManagementSystemLectureNotes/README.md
GeeksforgeeksDatabaseManagementSystemLectureNotes/__init__.py
GeeksforgeeksDatabaseManagementSystemLectureNotes/__main__.py
GeeksforgeeksDatabaseManagementSystemLectureNotes/file.epub
GeeksforgeeksDatabaseManagementSystemLectureNotes/index.html
GeeksforgeeksDatabaseManagementSystemLectureNotes/css/__init__.py
GeeksforgeeksDatabaseManagementSystemLectureNotes/css/annotations.css
GeeksforgeeksDatabaseManagementSystemLectureNotes/css/main.css
GeeksforgeeksDatabaseManagementSystemLectureNotes/css/normalize.css
GeeksforgeeksDatabaseManagementSystemLectureNotes/css/popup.css
GeeksforgeeksDatabaseManagementSystemLectureNotes/font/__init__.py
GeeksforgeeksDatabaseManagementSystemLectureNotes/font/fontello.eot
GeeksforgeeksDatabaseManagementSystemLectureNotes/font/fontello.svg
GeeksforgeeksDatabaseManagementSystemLectureNotes/font/fontello.ttf
GeeksforgeeksDatabaseManagementSystemLectureNotes/font/fontello.woff
GeeksforgeeksDatabaseManagementSystemLectureNotes/img/__init__.py
GeeksforgeeksDatabaseManagementSystemLectureNotes/img/annotator-glyph-sprite.png
GeeksforgeeksDatabaseManagementSystemLectureNotes/img/annotator-icon-sprite.png
GeeksforgeeksDatabaseManagementSystemLectureNotes/img/apple-touch-icon.png
GeeksforgeeksDatabaseManagementSystemLectureNotes/img/cancelfullscreen.png
GeeksforgeeksDatabaseManagementSystemLectureNotes/img/close.png
GeeksforgeeksDatabaseManagementSystemLectureNotes/img/fullscreen.png
GeeksforgeeksDatabaseManagementSystemLectureNotes/img/loader.gif
GeeksforgeeksDatabaseManagementSystemLectureNotes/img/menu-icon.png
GeeksforgeeksDatabaseManagementSystemLectureNotes/img/save.png
GeeksforgeeksDatabaseManagementSystemLectureNotes/img/saved.png
GeeksforgeeksDatabaseManagementSystemLectureNotes/img/settings-s.png
GeeksforgeeksDatabaseManagementSystemLectureNotes/img/settings.png
GeeksforgeeksDatabaseManagementSystemLectureNotes/img/star.png
geeksforgeeks_database_management_system_lecture_notes-2024.3.3.0.dist-info/METADATA
geeksforgeeks_database_management_system_lecture_notes-2024.3.3.0.dist-info/WHEEL
geeksforgeeks_database_management_system_lecture_notes-2024.3.3.0.dist-info/entry_points.txt
geeksforgeeks_database_management_system_lecture_notes-2024.3.3.0.dist-info/top_level.txt
geeksforgeeks_database_management_system_lecture_notes-2024.3.3.0.dist-info/RECORD
